README.txt
setup.cfg
setup.py
docs/HISTORY.txt
docs/INSTALL.txt
docs/LICENSE.GPL
docs/LICENSE.txt
redturtle/__init__.py
redturtle.externalizelink.egg-info/PKG-INFO
redturtle.externalizelink.egg-info/SOURCES.txt
redturtle.externalizelink.egg-info/dependency_links.txt
redturtle.externalizelink.egg-info/entry_points.txt
redturtle.externalizelink.egg-info/namespace_packages.txt
redturtle.externalizelink.egg-info/not-zip-safe
redturtle.externalizelink.egg-info/paster_plugins.txt
redturtle.externalizelink.egg-info/requires.txt
redturtle.externalizelink.egg-info/top_level.txt
redturtle/externalizelink/__init__.py
redturtle/externalizelink/configure.zcml
redturtle/externalizelink/tests.py
redturtle/externalizelink/browser/__init__.py
redturtle/externalizelink/browser/configure.zcml
redturtle/externalizelink/browser/externalize_link.js
redturtle/externalizelink/profiles/default/jsregistry.xml
redturtle/externalizelink/profiles/default/metadata.xml