Metadata-Version: 1.0
Name: redturtle.externalizelink
Version: 0.1.0alpha
Summary: A Plone product that open external link on different browser window in accessible way (even using XHTML Strict)
Home-page: http://svn.plone.org/svn/collective/redturtle.externalizelink
Author: RedTurtle Technology
Author-email: sviluppoplone@redturtle.net
License: GPL
Keywords: plone link external popup javascript xhtml-strict accessible
Platform: UNKNOWN
Classifier: Framework :: Plone
Classifier: Programming Language :: Python
Classifier: Topic :: Software Development :: Libraries :: Python Modules
